{"type":"FeatureCollection","features":[{"type":"Feature","geometry":{"geodesic":false,"type":"Point","coordinates":[-0.997129965372669,8.444163670723503]},"id":"+66+622","properties":{"Place":"Ghana","Region":"Northern","count":74970,"label":1}}]}